{
  "updated": 1749646716,
  "current": {
    "temp": 9.86,
    "icon": "01n"
  },
  "hourly": [
    {
      "dt": 1749643200,
      "temp": 9.68,
      "icon": "01n"
    },
    {
      "dt": 1749646800,
      "temp": 9.86,
      "icon": "01n"
    },
    {
      "dt": 1749650400,
      "temp": 9.63,
      "icon": "01n"
    },
    {
      "dt": 1749654000,
      "temp": 9.29,
      "icon": "01n"
    },
    {
      "dt": 1749657600,
      "temp": 8.83,
      "icon": "01n"
    },
    {
      "dt": 1749661200,
      "temp": 8.29,
      "icon": "01n"
    },
    {
      "dt": 1749664800,
      "temp": 7.42,
      "icon": "01n"
    },
    {
      "dt": 1749668400,
      "temp": 7.11,
      "icon": "01n"
    },
    {
      "dt": 1749672000,
      "temp": 6.94,
      "icon": "01n"
    },
    {
      "dt": 1749675600,
      "temp": 7.14,
      "icon": "01d"
    },
    {
      "dt": 1749679200,
      "temp": 9,
      "icon": "02d"
    },
    {
      "dt": 1749682800,
      "temp": 11.25,
      "icon": "03d"
    }
  ],
  "daily": [
    {
      "dt": 1749603600,
      "min": 7.72,
      "max": 17.09,
      "icon": "01d"
    },
    {
      "dt": 1749690000,
      "min": 6.94,
      "max": 16.37,
      "icon": "10d"
    },
    {
      "dt": 1749776400,
      "min": 10.65,
      "max": 14.56,
      "icon": "10d"
    },
    {
      "dt": 1749862800,
      "min": 10.7,
      "max": 15.04,
      "icon": "10d"
    },
    {
      "dt": 1749949200,
      "min": 9.1,
      "max": 16.47,
      "icon": "04d"
    },
    {
      "dt": 1750035600,
      "min": 7.51,
      "max": 16.57,
      "icon": "01d"
    },
    {
      "dt": 1750122000,
      "min": 10.55,
      "max": 17.56,
      "icon": "04d"
    }
  ]
}